[{"empId":1,"name":"Ruwan","profession":"Video Editor","contact":"0712812502","email":"john@gmail.com","workStatus":"Available"},{"empId":2,"name":"Ahamed","profession":"Video Editor","contact":"0712812502","email":"synchromary@gmail.com","workStatus":"Available"},{"empId":3,"name":"Prasanna","profession":"Graphic Designer","contact":"0712812502","email":"petervisuals@gmail.com","workStatus":"Available"},{"empId":4,"name":"Sunil","profession":"Graphic Designer","contact":"0712812502","email":"sunil87@yahoo.com","workStatus":"Available"},{"empId":5,"name":"Saman Weerasinghe","profession":"Content Writer","contact":"0727378910","email":"swblogs@gmail.com","workStatus":"Available"},{"empId":6,"name":"Jagath","profession":"Web Developer","contact":"0782341234","email":"jjsites@yahoo.com","workStatus":"Available"},{"empId":7,"name":"Alan","profession":"Graphic Designer","contact":"0718889999","email":"alan@gmail.com","workStatus":"Available"}]